kaptan/__about__.py
kaptan/__init__.py
kaptan/__main__.py
kaptan/_compat.py
kaptan/handlers/__init__.py
kaptan/handlers/dict_handler.py
kaptan/handlers/ini_handler.py
kaptan/handlers/json_handler.py
kaptan/handlers/pyfile_handler.py
kaptan/handlers/yaml_handler.py
kaptan-0.6.0.dist-info/AUTHORS
kaptan-0.6.0.dist-info/LICENSE
kaptan-0.6.0.dist-info/METADATA
kaptan-0.6.0.dist-info/WHEEL
kaptan-0.6.0.dist-info/entry_points.txt
kaptan-0.6.0.dist-info/top_level.txt
kaptan-0.6.0.dist-info/RECORD
